telemetry_datastore/__init__.py
telemetry_datastore-1.2.dist-info/LICENSE
telemetry_datastore-1.2.dist-info/METADATA
telemetry_datastore-1.2.dist-info/WHEEL
telemetry_datastore-1.2.dist-info/top_level.txt
telemetry_datastore-1.2.dist-info/RECORD
