Metadata-Version: 2.1
Name: telemetry-datastore
Version: 1.2
Summary: Telemetry data store
Home-page: https://github.com/Tangerino/telemetry-datastore.git
Author: Carlos Tangerino
Author-email: carlos.tangerino@gmail.com
License: UNKNOWN
Platform: UNKNOWN
Classifier: Programming Language :: Python :: 3
Classifier: License :: OSI Approved :: MIT License
Classifier: Operating System :: OS Independent
